gestao_aluguer/__init__.py
gestao_aluguer/gestão_aluguer_imoveis.py
gestao_aluguer-0.1.1.dist-info/licenses/LICENSE.txt
gestao_aluguer-0.1.1.dist-info/METADATA
gestao_aluguer-0.1.1.dist-info/WHEEL
gestao_aluguer-0.1.1.dist-info/top_level.txt
gestao_aluguer-0.1.1.dist-info/RECORD
