Metadata-Version: 2.4
Name: gestao_aluguer
Version: 0.1.1
Summary: Ferramenta para gestão de aluguer de imóveis.
Home-page: https://github.com/DasilvaCatarina/-gest-o-de-aluguer-de-im-veis
Author: Catarina Silva,João Pedro Pinto Costa,Ana Martins,Daniel Teixeira da Silva
Author-email: seu@email.com
License-File: LICENSE.txt
Requires-Dist: pandas
Requires-Dist: matplotlib
Requires-Dist: datetime
Requires-Dist: tabulate
Dynamic: author
Dynamic: author-email
Dynamic: description
Dynamic: description-content-type
Dynamic: home-page
Dynamic: license-file
Dynamic: requires-dist
Dynamic: summary
